{"deltaAltitude":"0.00","pace":"5.71","nextPoint":{"distance":138,"lon":-1.4779579999999999,"alt":2.156429,"bearing":104,"lat":43.497353},"speed":105,"img":"http://maps.googleapis.com/maps/api/streetview?sensor=false&key=AIzaSyB2rIeVeFVjygF-MqobdN3giz_SnZkiJ7M&size=640x450&location=43.4974,-1.4782&heading=108","calcDistance":112,"pulse":0,"destPower":50,"nextImg":"http://maps.googleapis.com/maps/api/streetview?sensor=false&key=AIzaSyB2rIeVeFVjygF-MqobdN3giz_SnZkiJ7M&size=640x450&location=43.4974,-1.4780&heading=104","pedalRpm":66,"point":{"distance":118,"lon":-1.478194,"alt":2.1719,"bearing":108,"lat":43.497408},"time":"00:00:47","distance":1,"realPower":0,"energy":0}