{"deltaAltitude":"0.00","pace":"5.88","nextPoint":{"distance":40,"lon":-122.409233,"alt":29.566200000000002,"bearing":140,"lat":37.784470999999996},"speed":102,"img":"http://maps.googleapis.com/maps/api/streetview?sensor=false&key=AIzaSyB2rIeVeFVjygF-MqobdN3giz_SnZkiJ7M&size=640x450&location=37.7846,-122.4094&heading=148","calcDistance":15,"pulse":0,"destPower":50,"nextImg":"http://maps.googleapis.com/maps/api/streetview?sensor=false&key=AIzaSyB2rIeVeFVjygF-MqobdN3giz_SnZkiJ7M&size=640x450&location=37.7845,-122.4092&heading=140","pedalRpm":64,"point":{"distance":20,"lon":-122.409352,"alt":29.82,"bearing":148,"lat":37.784622999999996},"time":"00:00:17","distance":0,"realPower":0,"energy":0}